seal/__init__.py
seal/seal.py
seal/cache/__init__.py
seal/cache/cache.py
seal/cache/lru_cache.py
seal/config/__init__.py
seal/config/configuration.py
seal/context/__init__.py
seal/context/context.py
seal/db/__init__.py
seal/db/condition.py
seal/db/insert_wrapper.py
seal/db/query_wrapper.py
seal/db/result.py
seal/db/sql_builder.py
seal/db/structures.py
seal/db/transaction.py
seal/db/update_wrapper.py
seal/db/wrapper.py
seal/db/mysql/__init__.py
seal/db/mysql/executor.py
seal/db/mysql/mysql_connection.py
seal/db/mysql/mysql_data_source.py
seal/db/mysql/table_info.py
seal/db/protocol/__init__.py
seal/db/protocol/data_source_protocol.py
seal/db/protocol/database_connection_protocol.py
seal/db/protocol/entity_protocol.py
seal/db/protocol/executor_protocol.py
seal/db/sqlite/__init__.py
seal/db/sqlite/executor.py
seal/db/sqlite/sqlite_connection.py
seal/db/sqlite/sqlite_data_source.py
seal/db/sqlite/table_info.py
seal/enum/__init__.py
seal/enum/connection_status.py
seal/enum/dialects.py
seal/enum/operator.py
seal/enum/result_type.py
seal/exception/__init__.py
seal/exception/business_exception.py
seal/exception/unsupported_exception.py
seal/job/__init__.py
seal/job/_job_manager.py
seal/model/__init__.py
seal/model/response.py
seal/router/__init__.py
seal/router/router.py
seal/types/__init__.py
seal/types/types.py
seal/utils/__init__.py
seal/utils/decorator_utils.py
seal/utils/list_utils.py
seal/utils/str_utils.py
seal/ws/__init__.py
seal/ws/_ws.py
seal/ws/ws_dispatcher.py
seal/ws/ws_handler.py
py_seal-0.10.0.dist-info/LICENSE
py_seal-0.10.0.dist-info/METADATA
py_seal-0.10.0.dist-info/WHEEL
py_seal-0.10.0.dist-info/top_level.txt
py_seal-0.10.0.dist-info/RECORD
