Metadata-Version: 2.1
Name: py-seal
Version: 0.10.0
Summary: 一个python快速web开发框架
Author: melon
License-File: LICENSE
